{
  "name": "mitigation_cb2024-350mt",
  "data": [
    {
      "seriesName": "FT_SRV",
      "seriesValues": [
        [
          2018,
          0.235371206278147
        ],
        [
          2019,
          0.235371191744909
        ],
        [
          2020,
          0.308999998458082
        ],
        [
          2021,
          0.0069002116543625
        ],
        [
          2022,
          0.308999997879004
        ],
        [
          2023,
          0.624449996955251
        ],
        [
          2024,
          0.955672495378938
        ],
        [
          2025,
          0.5173752535117024
        ],
        [
          2028,
          0.0
        ],
        [
          2029,
          0.300000071505816
        ],
        [
          2030,
          0.615000073420692
        ],
        [
          2031,
          0.0
        ],
        [
          2034,
          0.0
        ],
        [
          2035,
          0.0
        ],
        [
          2036,
          0.0
        ],
        [
          2037,
          0.0
        ]
      ]
    },
    {
      "seriesName": "FT_IND",
      "seriesValues": [
        [
          2019,
          0.0
        ],
        [
          2020,
          0.0233712054715481
        ],
        [
          2021,
          0.228470993248507
        ],
        [
          2022,
          0.359999997879183
        ],
        [
          2023,
          2.35594984310408
        ],
        [
          2024,
          2.82080520278997
        ],
        [
          2025,
          4.214400493215069
        ],
        [
          2026,
          5.8781311065151804
        ],
        [
          2027,
          7.25375733938996
        ],
        [
          2028,
          8.90450876429299
        ],
        [
          2029,
          10.5854105355365
        ],
        [
          2030,
          12.64749265538786
        ],
        [
          2031,
          7.78126963967952
        ],
        [
          2032,
          6.447959227084439
        ],
        [
          2033,
          6.10621755953647
        ],
        [
          2034,
          6.3633834254858295
        ],
        [
          2035,
          7.78126502127497
        ],
        [
          2036,
          7.781267954134419
        ],
        [
          2037,
          7.78126834571059
        ],
        [
          2038,
          7.35025505774236
        ],
        [
          2039,
          7.35025572936987
        ],
        [
          2040,
          7.3502553153656205
        ],
        [
          2041,
          7.3502565393699495
        ],
        [
          2042,
          8.5469675747493
        ],
        [
          2043,
          6.565507059984389
        ],
        [
          2044,
          5.68793560287228
        ],
        [
          2045,
          4.90754923682644
        ],
        [
          2046,
          0.047365347629253596
        ],
        [
          2047,
          1.335717799921862e-06
        ],
        [
          2048,
          0.0
        ],
        [
          2049,
          0.0
        ],
        [
          2050,
          0.0
        ],
        [
          2051,
          0.0
        ]
      ]
    },
    {
      "seriesName": "FT_RSD",
      "seriesValues": [
        [
          2023,
          0.0
        ],
        [
          2024,
          2.29362635508047e-06
        ],
        [
          2025,
          0.0
        ],
        [
          2026,
          0.0
        ],
        [
          2027,
          0.0
        ],
        [
          2028,
          0.0
        ],
        [
          2029,
          0.0
        ],
        [
          2030,
          0.0
        ],
        [
          2031,
          0.0
        ],
        [
          2032,
          1.333310776688605
        ],
        [
          2033,
          1.675052443682151
        ],
        [
          2034,
          1.417886545366027
        ],
        [
          2035,
          4.80947236872513e-06
        ],
        [
          2036,
          1.882179472919256e-06
        ],
        [
          2037,
          1.4976352479401658e-06
        ],
        [
          2038,
          1.4023943881983509e-06
        ],
        [
          2039,
          0.0
        ],
        [
          2040,
          1.1631662966839658e-06
        ],
        [
          2041,
          0.0
        ],
        [
          2042,
          0.473341084512104
        ],
        [
          2043,
          0.00039362759162340003
        ],
        [
          2044,
          0.081885072545068
        ],
        [
          2045,
          0.303897230177559
        ],
        [
          2046,
          4.01835515729272
        ],
        [
          2047,
          3.677894912077849
        ],
        [
          2048,
          3.9948282657031435
        ],
        [
          2049,
          3.8223185200024985
        ],
        [
          2050,
          3.6498086666287897
        ],
        [
          2051,
          3.6498083875894984
        ]
      ]
    }
  ]
}